__init__.py
game_of_life/__init__.py
game_of_life/cell.py
game_of_life/enums.py
game_of_life/game_grid.py
game_of_life_YetiYetYet-0.1.0.dist-info/LICENCE
game_of_life_YetiYetYet-0.1.0.dist-info/METADATA
game_of_life_YetiYetYet-0.1.0.dist-info/WHEEL
game_of_life_YetiYetYet-0.1.0.dist-info/top_level.txt
game_of_life_YetiYetYet-0.1.0.dist-info/RECORD
