Metadata-Version: 2.1
Name: game-of-life-YetiYetYet
Version: 0.1.0
Summary: This package is a Python implementation of Conway's Game of Life,a cellular automaton devised by the British mathematician John Horton Conway in 1970. The game is a zero-player game, meaning that its evolution is determined by its initial state, requiring no further input. One interacts with the Game of Life by creating an initial configuration and observing how it evolves.
Author-email: Alexis BEHIER <alexisbehier22@gmail.com>
Project-URL: Homepage, https://github.com/YetiYetYet/game-of-life-python
Project-URL: Bug Tracker, https://github.com/YetiYetYet/game-of-life-python/issues
Classifier: Programming Language :: Python :: 3
Classifier: License :: OSI Approved :: MIT License
Classifier: Operating System :: OS Independent
Requires-Python: >=3.12
License-File: LICENCE
